bigdata_lib/__init__.py
bigdata_lib/adjacency_list.py
bigdata_lib/adjacency_matrix.py
bigdata_lib/avl_tree.py
bigdata_lib/b_tree.py
bigdata_lib/bplus_tree.py
bigdata_lib/fenwick_tree.py
bigdata_lib/red_black_tree.py
bigdata_lib/segment_tree.py
bigdata_lib/skip_list.py
bigdata_lib/trie_structure.py
bigdata_lib/utils.py
bigdata_lib-0.2.dist-info/METADATA
bigdata_lib-0.2.dist-info/WHEEL
bigdata_lib-0.2.dist-info/top_level.txt
bigdata_lib-0.2.dist-info/RECORD
