Metadata-Version: 2.1
Name: bigdata_lib
Version: 0.2
Summary: A Python library for various big data structures including graphs, trees, and more.
Home-page: https://github.com/AdityaSrivastavDS/bigdata_lib
Author: Aditya
Author-email: adityathestar2006@gmail.com
Classifier: Programming Language :: Python :: 3
Classifier: Programming Language :: Python :: 3.6
Classifier: Programming Language :: Python :: 3.7
Classifier: Programming Language :: Python :: 3.8
Classifier: Programming Language :: Python :: 3.9
Classifier: License :: OSI Approved :: Apache Software License
Classifier: Operating System :: OS Independent
Requires-Python: >=3.6
